{
  "$schema": "http://json-schema.org/schema",
  "executors": {
    "tsc": {
      "implementation": "./src/executors/tsc/executor",
      "schema": "./src/executors/tsc/schema.json",
      "description": "TSC executor"
    },
    "publishable": {
      "implementation": "./src/executors/publishable/executor",
      "schema": "./src/executors/publishable/schema.json",
      "description": "fix output of @nx/js"
    },
    "execute": {
      "implementation": "./src/executors/execute/executor",
      "schema": "./src/executors/execute/schema.json",
      "description": "execute executor",
      "hasher": "./src/executors/execute/hasher"
    }
  }
}
